{
  "sam": [
    {
      "source": "CSES",
      "name": "Distinct Colors",
      "id": "1139",
      "difficulty": "Easy",
      "starred": false,
      "tags": ["Merging"],
      "solID": null,
      "solQuality": "ok",
      "url": "https://cses.fi/problemset/task/1139",
      "uniqueID": "https://cses.fi/problemset/task/1139"
    }
  ],
  "general": [
    {
      "source": "CF",
      "name": "Lomsat gelral",
      "id": "contest/600/problem/E",
      "difficulty": "Normal",
      "starred": false,
      "tags": ["Merging"],
      "solID": null,
      "solQuality": "ok",
      "url": "https://codeforces.com/contest/600/problem/E",
      "uniqueID": "https://codeforces.com/contest/600/problem/E"
    },
    {
      "source": "Plat",
      "name": "Promotion Counting",
      "id": "696",
      "difficulty": "Normal",
      "starred": false,
      "tags": ["Merging", "Indexed Set"],
      "solID": "usaco-696",
      "solQuality": "ok",
      "url": "http://www.usaco.org/index.php?page=viewproblem2&cpid=696",
      "uniqueID": "http://www.usaco.org/index.php?page=viewproblem2&cpid=696"
    },
    {
      "source": "Plat",
      "name": "Disruption",
      "id": "842",
      "difficulty": "Normal",
      "starred": false,
      "tags": ["Merging"],
      "solID": null,
      "solQuality": "ok",
      "url": "http://www.usaco.org/index.php?page=viewproblem2&cpid=842",
      "uniqueID": "http://www.usaco.org/index.php?page=viewproblem2&cpid=842"
    },
    {
      "source": "POI",
      "name": "2011 - Tree Rotations",
      "id": "https://szkopul.edu.pl/problemset/problem/sUe3qzxBtasek-RAWmZaxY_p/site/?key=statement",
      "difficulty": "Normal",
      "starred": false,
      "tags": ["Merging", "Indexed Set"],
      "solID": "https://github.com/mostafa-saad/MyCompetitiveProgramming/blob/master/Olympiad/POI/official/2011/editorial/rot.pdf",
      "solQuality": "ok",
      "url": "https://szkopul.edu.pl/problemset/problem/sUe3qzxBtasek-RAWmZaxY_p/site/?key=statement",
      "uniqueID": "https://szkopul.edu.pl/problemset/problem/sUe3qzxBtasek-RAWmZaxY_p/site/?key=statement"
    },
    {
      "source": "IOI",
      "name": "2011 - Race",
      "id": "https://oj.uz/problem/view/IOI11_race",
      "difficulty": "Normal",
      "starred": true,
      "tags": ["Centroid", "Merging"],
      "solID": "",
      "solQuality": "ok",
      "url": "https://oj.uz/problem/view/IOI11_race",
      "uniqueID": "https://oj.uz/problem/view/IOI11_race"
    },
    {
      "source": "JOI",
      "name": "2020 - Joitter",
      "id": "https://oj.uz/problem/view/JOI20_joitter2",
      "difficulty": "Hard",
      "starred": false,
      "tags": ["Merging"],
      "solID": "joi-20-joitter",
      "solQuality": "ok",
      "url": "https://oj.uz/problem/view/JOI20_joitter2",
      "uniqueID": "https://oj.uz/problem/view/JOI20_joitter2"
    },
    {
      "source": "COI",
      "name": "2009 - Loza",
      "id": "https://dmoj.ca/problem/coi09p3",
      "difficulty": "Hard",
      "starred": false,
      "tags": ["Merging"],
      "solID": "",
      "solQuality": "ok",
      "url": "https://dmoj.ca/problem/coi09p3",
      "uniqueID": "https://dmoj.ca/problem/coi09p3"
    },
    {
      "source": "JOI",
      "name": "2019 - Virus",
      "id": "https://oj.uz/problem/view/JOI19_virus",
      "difficulty": "Very Hard",
      "starred": false,
      "tags": ["Merging", "SCC"],
      "solID": "",
      "solQuality": "ok",
      "url": "https://oj.uz/problem/view/JOI19_virus",
      "uniqueID": "https://oj.uz/problem/view/JOI19_virus"
    }
  ]
}
