{
  "MODULE_ID": "sqrt",
  "sam": [
    {
      "uniqueId": "cses-1648",
      "name": "Dynamic Range Sum Queries",
      "url": "https://cses.fi/problemset/task/1648",
      "source": "CSES",
      "difficulty": "Very Easy",
      "isStarred": false,
      "tags": ["Sqrt"],
      "solutionMetadata": {
        "kind": "none"
      }
    }
  ],
  "fst": [
    {
      "uniqueId": "cf-576C",
      "name": "Points on Plane",
      "url": "https://codeforces.com/contest/576/problem/C",
      "source": "CF",
      "difficulty": "Easy",
      "isStarred": false,
      "tags": ["Sqrt"],
      "solutionMetadata": {
        "kind": "link",
        "url": "https://codeforces.com/blog/entry/20226"
      }
    },
    {
      "uniqueId": "joi-18-BitarosBirthday",
      "name": "2018 - Bitaro's Birthday",
      "url": "https://oj.uz/problem/view/JOI18_bitaro",
      "source": "JOI",
      "difficulty": "Easy",
      "isStarred": false,
      "tags": ["Sqrt"],
      "solutionMetadata": {
        "kind": "none"
      }
    },
    {
      "uniqueId": "poi-17-containers",
      "name": "2017 - Containers",
      "url": "https://szkopul.edu.pl/problemset/problem/oNnWY6ZuzzhvG-jCmijiXkIk/site/?key=statement",
      "source": "POI",
      "difficulty": "Easy",
      "isStarred": false,
      "tags": ["Sqrt"],
      "solutionMetadata": {
        "kind": "internal"
      }
    },
    {
      "uniqueId": "cf-13E",
      "name": "Holes",
      "url": "https://codeforces.com/problemset/problem/13/E",
      "source": "CF",
      "difficulty": "Easy",
      "isStarred": false,
      "tags": ["Sqrt"],
      "solutionMetadata": {
        "kind": "autogen-label-from-site",
        "site": "CF"
      }
    },
    {
      "uniqueId": "cf-877F",
      "name": "Ann and Books",
      "url": "https://codeforces.com/contest/877/problem/F",
      "source": "CF",
      "difficulty": "Easy",
      "isStarred": false,
      "tags": ["Sqrt"],
      "solutionMetadata": {
        "kind": "autogen-label-from-site",
        "site": "CF"
      }
    },
    {
      "uniqueId": "ys-StaticRangeInversionsQuery",
      "name": "Static Range Inversions Query",
      "url": "https://judge.yosupo.jp/problem/static_range_inversions_query",
      "source": "YS",
      "difficulty": "Normal",
      "isStarred": false,
      "tags": ["Sqrt"],
      "solutionMetadata": {
        "kind": "internal"
      }
    },
    {
      "uniqueId": "cf-86D",
      "name": "Powerful array",
      "url": "https://codeforces.com/contest/86/problem/D",
      "source": "CF",
      "difficulty": "Normal",
      "isStarred": false,
      "tags": ["Mo's Algorithm"],
      "solutionMetadata": {
        "kind": "autogen-label-from-site",
        "site": "CF"
      }
    },
    {
      "uniqueId": "apio-19-bridges",
      "name": "2019 - Bridges",
      "url": "https://oj.uz/problem/view/APIO19_bridges",
      "source": "APIO",
      "difficulty": "Hard",
      "isStarred": false,
      "tags": ["Sqrt"],
      "solutionMetadata": {
        "kind": "internal"
      }
    },
    {
      "uniqueId": "joi-18-SnakeEscaping",
      "name": "2018 - Snake Escaping",
      "url": "https://oj.uz/problem/view/JOI18_snake_escaping",
      "source": "JOI",
      "difficulty": "Hard",
      "isStarred": false,
      "tags": ["SOS DP"],
      "solutionMetadata": {
        "kind": "internal"
      }
    },
    {
      "uniqueId": "usaco-841",
      "name": "Train Tracking",
      "url": "http://www.usaco.org/index.php?page=viewproblem2&cpid=841",
      "source": "Plat",
      "difficulty": "Very Hard",
      "isStarred": false,
      "tags": ["Sqrt"],
      "solutionMetadata": {
        "kind": "USACO",
        "usacoId": "841"
      }
    },
    {
      "uniqueId": "dmoj-FluidDynamics",
      "name": "Fluid Dynamics",
      "url": "https://dmoj.ca/problem/dmopc19c7p7",
      "source": "DMOJ",
      "difficulty": "Very Hard",
      "isStarred": false,
      "tags": ["Sqrt"],
      "solutionMetadata": {
        "kind": "internal"
      }
    },
    {
      "uniqueId": "dmoj-ArithmeticSubtrees",
      "name": "Arithmetic Subtrees",
      "url": "https://dmoj.ca/problem/wac1p7",
      "source": "DMOJ",
      "difficulty": "Very Hard",
      "isStarred": false,
      "tags": ["Sqrt"],
      "solutionMetadata": {
        "kind": "autogen-label-from-site",
        "site": "DMOJ"
      }
    }
  ],
  "bad": [
    {
      "uniqueId": "joi-19-examination",
      "name": "2019 - Examination",
      "url": "https://oj.uz/problem/view/JOI19_examination",
      "source": "JOI",
      "difficulty": "Normal",
      "isStarred": false,
      "tags": ["Mo's Algorithm", "2DRQ"],
      "solutionMetadata": {
        "kind": "none"
      }
    },
    {
      "uniqueId": "ioi-09-regions",
      "name": "2009 - Regions",
      "url": "https://oj.uz/problem/view/IOI09_regions",
      "source": "IOI",
      "difficulty": "Normal",
      "isStarred": false,
      "tags": ["Sqrt"],
      "solutionMetadata": {
        "kind": "IOI",
        "year": 2009
      }
    },
    {
      "uniqueId": "usaco-817",
      "name": "New Barns",
      "url": "http://www.usaco.org/index.php?page=viewproblem2&cpid=817",
      "source": "Plat",
      "difficulty": "Hard",
      "isStarred": false,
      "tags": ["Sqrt"],
      "solutionMetadata": {
        "kind": "USACO",
        "usacoId": "817"
      }
    },
    {
      "uniqueId": "cf-1254D",
      "name": "Tree Queries",
      "url": "https://codeforces.com/contest/1254/problem/D",
      "source": "CF",
      "difficulty": "Hard",
      "isStarred": false,
      "tags": ["Sqrt"],
      "solutionMetadata": {
        "kind": "autogen-label-from-site",
        "site": "CF"
      }
    },
    {
      "uniqueId": "cf-1017G",
      "name": "The Tree",
      "url": "https://codeforces.com/contest/1017/problem/G",
      "source": "CF",
      "difficulty": "Hard",
      "isStarred": false,
      "tags": ["HLD"],
      "solutionMetadata": {
        "kind": "internal"
      }
    },
    {
      "uniqueId": "tlx-TreeGame",
      "name": "Tree Game",
      "url": "https://tlx.toki.id/problems/troc-14/H/",
      "source": "TLX",
      "difficulty": "Hard",
      "isStarred": false,
      "tags": ["Sqrt"],
      "solutionMetadata": {
        "kind": "autogen-label-from-site",
        "site": "TLX"
      }
    },
    {
      "uniqueId": "csa-ShoppingTime",
      "name": "Shopping Time",
      "url": "https://csacademy.com/contest/archive/task/shopping-time",
      "source": "CSA",
      "difficulty": "Hard",
      "isStarred": false,
      "tags": ["Sqrt"],
      "solutionMetadata": {
        "kind": "autogen-label-from-site",
        "site": "CSA"
      }
    },
    {
      "uniqueId": "usaco-534",
      "name": "Fencing the Herd",
      "url": "http://www.usaco.org/index.php?page=viewproblem2&cpid=534",
      "source": "Old Gold",
      "difficulty": "Hard",
      "isStarred": false,
      "tags": ["Convex"],
      "solutionMetadata": {
        "kind": "USACO",
        "usacoId": "534"
      }
    },
    {
      "uniqueId": "cf-1178G",
      "name": "The Awesomest Vertex",
      "url": "https://codeforces.com/contest/1178/problem/G",
      "source": "CF",
      "difficulty": "Very Hard",
      "isStarred": false,
      "tags": ["Convex"],
      "solutionMetadata": {
        "kind": "autogen-label-from-site",
        "site": "CF"
      }
    },
    {
      "uniqueId": "ioi-11-DancingElephants",
      "name": "2011 - Dancing Elephants",
      "url": "https://oj.uz/problem/view/IOI11_elephants",
      "source": "IOI",
      "difficulty": "Very Hard",
      "isStarred": false,
      "tags": ["Sqrt"],
      "solutionMetadata": {
        "kind": "IOI",
        "year": 2011
      }
    },
    {
      "uniqueId": "usaco-793",
      "name": "Cow At Large",
      "url": "http://www.usaco.org/index.php?page=viewproblem2&cpid=793",
      "source": "Plat",
      "difficulty": "Very Hard",
      "isStarred": false,
      "tags": ["Sqrt"],
      "solutionMetadata": {
        "kind": "internal"
      }
    },
    {
      "uniqueId": "ioi-15-teams",
      "name": "2015 - Teams",
      "url": "https://oj.uz/problem/view/IOI15_teams",
      "source": "IOI",
      "difficulty": "Very Hard",
      "isStarred": false,
      "tags": ["2DRQ"],
      "solutionMetadata": {
        "kind": "IOI",
        "year": 2015
      }
    }
  ]
}
