{
  "MODULE_ID": "intro-bitwise",
  "probs": [
    {
      "uniqueId": "cf-1017D",
      "name": "The Wu",
      "url": "https://codeforces.com/contest/1017/problem/D",
      "source": "CF",
      "difficulty": "Normal",
      "isStarred": false,
      "tags": ["Math", "Complete Search"],
      "solutionMetadata": {
        "kind": "autogen-label-from-site",
        "site": "CF"
      }
    },
    {
      "uniqueId": "cf-1338A",
      "name": "Powered Addition",
      "url": "https://codeforces.com/contest/1338/problem/A",
      "source": "CF",
      "difficulty": "Normal",
      "isStarred": false,
      "tags": ["Math", "Greedy"],
      "solutionMetadata": {
        "kind": "autogen-label-from-site",
        "site": "CF"
      }
    },
    {
      "uniqueId": "cf-1368D",
      "name": "AND, OR, and square sum",
      "url": "https://codeforces.com/contest/1368/problem/D",
      "source": "CF",
      "difficulty": "Normal",
      "isStarred": false,
      "tags": ["Math", "Greedy"],
      "solutionMetadata": {
        "kind": "autogen-label-from-site",
        "site": "CF"
      }
    },
    {
      "uniqueId": "cf-1466E",
      "name": "Apollo vs Pan",
      "url": "https://codeforces.com/contest/1466/problem/E",
      "source": "CF",
      "difficulty": "Normal",
      "isStarred": false,
      "tags": ["Math"],
      "solutionMetadata": {
        "kind": "autogen-label-from-site",
        "site": "CF"
      }
    },
    {
      "uniqueId": "cf-1088D",
      "name": "Ehab and another another xor problem",
      "url": "https://codeforces.com/contest/1088/problem/D",
      "source": "CF",
      "difficulty": "Hard",
      "isStarred": false,
      "tags": ["Math", "Interactive"],
      "solutionMetadata": {
        "kind": "autogen-label-from-site",
        "site": "CF"
      }
    }
  ]
}
