{
  "MODULE_ID": "shortest-paths",
  "sample": [
    {
      "uniqueId": "cses-1671",
      "name": "Shortest Routes I",
      "url": "https://cses.fi/problemset/task/1671",
      "source": "CSES",
      "difficulty": "Easy",
      "isStarred": false,
      "tags": ["SP"],
      "solutionMetadata": {
        "kind": "sketch",
        "sketch": "equivalent to [Kattis SSSP Non-Negative](https://open.kattis.com/problems/shortestpath1)"
      }
    }
  ],
  "dijk": [
    {
      "uniqueId": "cses-1195",
      "name": "Flight Discount",
      "url": "https://cses.fi/problemset/task/1195",
      "source": "CSES",
      "difficulty": "Easy",
      "isStarred": false,
      "tags": ["SP"],
      "solutionMetadata": {
        "kind": "internal"
      }
    },
    {
      "uniqueId": "usaco-969",
      "name": "Milk Pumping",
      "url": "http://www.usaco.org/index.php?page=viewproblem2&cpid=969",
      "source": "Gold",
      "difficulty": "Easy",
      "isStarred": false,
      "tags": ["SP"],
      "solutionMetadata": {
        "kind": "internal"
      }
    },
    {
      "uniqueId": "usaco-717",
      "name": "Why Did the Cow Cross the Road",
      "url": "http://www.usaco.org/index.php?page=viewproblem2&cpid=717",
      "source": "Gold",
      "difficulty": "Easy",
      "isStarred": false,
      "tags": ["SP"],
      "solutionMetadata": {
        "kind": "internal"
      }
    },
    {
      "uniqueId": "usaco-861",
      "name": "Fine Dining",
      "url": "http://www.usaco.org/index.php?page=viewproblem2&cpid=861",
      "source": "Gold",
      "difficulty": "Easy",
      "isStarred": false,
      "tags": ["SP"],
      "solutionMetadata": {
        "kind": "internal",
        "usacoId": "861"
      }
    },
    {
      "uniqueId": "usaco-899",
      "name": "Shortcut",
      "url": "http://www.usaco.org/index.php?page=viewproblem2&cpid=899",
      "source": "Gold",
      "difficulty": "Normal",
      "isStarred": false,
      "tags": ["SP"],
      "solutionMetadata": {
        "kind": "internal"
      }
    },
    {
      "uniqueId": "cses-1202",
      "name": "Investigation",
      "url": "https://cses.fi/problemset/task/1202",
      "source": "CSES",
      "difficulty": "Normal",
      "isStarred": true,
      "tags": ["SP"],
      "solutionMetadata": {
        "kind": "internal"
      }
    },
    {
      "uniqueId": "kattis-robotturtles",
      "name": "Robot Turtles",
      "url": "https://open.kattis.com/problems/robotturtles",
      "source": "Kattis",
      "difficulty": "Normal",
      "isStarred": false,
      "tags": ["SP"],
      "solutionMetadata": {
        "kind": "internal"
      }
    },
    {
      "uniqueId": "cses-1196",
      "name": "Flight Routes",
      "url": "https://cses.fi/problemset/task/1196",
      "source": "CSES",
      "difficulty": "Normal",
      "isStarred": false,
      "tags": ["SP"],
      "solutionMetadata": {
        "kind": "internal"
      }
    },
    {
      "uniqueId": "ioi-11-crocodile",
      "name": "2011 - Crocodile",
      "url": "https://oj.uz/problem/view/IOI11_crocodile",
      "source": "IOI",
      "difficulty": "Hard",
      "isStarred": false,
      "tags": ["SP"],
      "solutionMetadata": {
        "kind": "IOI",
        "year": 2011
      }
    },
    {
      "uniqueId": "joi-18-CommuterPass",
      "name": "2018 - Commuter Pass",
      "url": "https://oj.uz/problem/view/JOI18_commuter_pass",
      "source": "JOI",
      "difficulty": "Hard",
      "isStarred": true,
      "tags": ["SP", "DP"],
      "solutionMetadata": {
        "kind": "internal"
      }
    },
    {
      "uniqueId": "joi-21-robot",
      "name": "2021 - Robot",
      "url": "https://oj.uz/problem/view/JOI21_ho_t4",
      "source": "JOI",
      "difficulty": "Hard",
      "isStarred": true,
      "tags": ["SP"],
      "solutionMetadata": {
        "kind": "internal"
      }
    },
    {
      "uniqueId": "apio-11-FindThePath",
      "name": "2011 - Find the Path",
      "url": "https://dmoj.ca/problem/apio11p2",
      "source": "APIO",
      "difficulty": "Hard",
      "isStarred": false,
      "tags": ["SP", "Geometry"],
      "solutionMetadata": {
        "kind": "internal"
      }
    },
    {
      "uniqueId": "balkan-12-ShortestPaths",
      "name": "2012 - Shortest Paths",
      "url": "https://www.acmicpc.net/problem/5250",
      "source": "Balkan OI",
      "difficulty": "Hard",
      "isStarred": true,
      "tags": ["SP"],
      "solutionMetadata": {
        "kind": "internal"
      }
    },
    {
      "uniqueId": "balkan-15-circus",
      "name": "2015 - Circus",
      "url": "https://oj.uz/problem/view/Balkan15_CIRCUS",
      "source": "Balkan OI",
      "difficulty": "Very Hard",
      "isStarred": false,
      "tags": ["SP", "Stack"],
      "solutionMetadata": {
        "kind": "none"
      }
    }
  ],
  "apspSam": [
    {
      "uniqueId": "cses-1672",
      "name": "Shortest Routes II",
      "url": "https://cses.fi/problemset/task/1672",
      "source": "CSES",
      "difficulty": "Easy",
      "isStarred": false,
      "tags": ["APSP"],
      "solutionMetadata": {
        "kind": "none"
      }
    }
  ],
  "apsp": [
    {
      "uniqueId": "usaco-971",
      "name": "Moortal Cowmbat",
      "url": "http://www.usaco.org/index.php?page=viewproblem2&cpid=971",
      "source": "Gold",
      "difficulty": "Hard",
      "isStarred": false,
      "tags": ["APSP", "DP"],
      "solutionMetadata": {
        "kind": "internal"
      }
    }
  ]
}
