[
  {
    "source": "YS",
    "name": "Two-Edge-Connected Components",
    "id": "two_edge_connected_components",
    "difficulty": "Easy",
    "starred": false,
    "tags": ["2CC"],
    "solID": "Split the graph into its biconnected components. See Infoarena - Biconex for how to do this.",
    "solQuality": "ok",
    "url": "https://judge.yosupo.jp/problem/two_edge_connected_components",
    "uniqueID": "https://judge.yosupo.jp/problem/two_edge_connected_components"
  },
  {
    "source": "Plat",
    "name": "Disruption",
    "id": "842",
    "difficulty": "Normal",
    "starred": false,
    "tags": ["Merging"],
    "solID": null,
    "solQuality": "ok",
    "url": "http://www.usaco.org/index.php?page=viewproblem2&cpid=842",
    "uniqueID": "http://www.usaco.org/index.php?page=viewproblem2&cpid=842"
  },
  {
    "source": "CEOI",
    "name": "2017 - One-Way Streets",
    "id": "https://oj.uz/problem/view/CEOI17_oneway",
    "difficulty": "Easy",
    "starred": false,
    "tags": ["BCC"],
    "solID": "",
    "solQuality": "ok",
    "url": "https://oj.uz/problem/view/CEOI17_oneway",
    "uniqueID": "https://oj.uz/problem/view/CEOI17_oneway"
  },
  {
    "source": "CSES",
    "name": "Forbidden Cities",
    "id": "1705",
    "difficulty": "Normal",
    "starred": false,
    "tags": ["BCC"],
    "solID": "",
    "solQuality": "ok",
    "url": "https://cses.fi/problemset/task/1705",
    "uniqueID": "https://cses.fi/problemset/task/1705"
  },
  {
    "source": "CSES",
    "name": "Strongly Connected Edges",
    "id": "2177",
    "difficulty": "Easy",
    "starred": false,
    "tags": ["BCC"],
    "solID": "cses-2177",
    "solQuality": "ok",
    "url": "https://cses.fi/problemset/task/2177",
    "uniqueID": "https://cses.fi/problemset/task/2177"
  },
  {
    "source": "POI",
    "name": "2008 - Blockade",
    "id": "eDt8w290owtatmCjad0O0ywk/site/?key=statement",
    "difficulty": "Normal",
    "starred": false,
    "tags": ["BCC"],
    "solID": "Instead of counting the number of bad pairs, count the number of good pairs and subtract that from the total number of all pairs. Notice how if we remove a node, we get several connected components. We can then use biconnected components to determine the sizes of these components and so we can count the number of good pairs after removing each node.",
    "solQuality": "ok",
    "url": "https://szkopul.edu.pl/problemset/problem/eDt8w290owtatmCjad0O0ywk/site/?key=statement",
    "uniqueID": "https://szkopul.edu.pl/problemset/problem/eDt8w290owtatmCjad0O0ywk/site/?key=statement"
  },
  {
    "source": "APIO",
    "name": "2018 - Duathlon",
    "id": "APIO18_duathlon",
    "difficulty": "Normal",
    "starred": false,
    "tags": ["BCC"],
    "solID": "apio-18-duathlon",
    "solQuality": "ok",
    "url": "https://oj.uz/problem/view/APIO18_duathlon",
    "uniqueID": "https://oj.uz/problem/view/APIO18_duathlon"
  },
  {
    "source": "POI",
    "name": "2016 - Amusing Journeys",
    "id": "YY6-3ua-C1rt7q-97laWc0UP/site/",
    "difficulty": "Normal",
    "starred": false,
    "tags": ["BCC"],
    "solID": "",
    "solQuality": "ok",
    "url": "https://szkopul.edu.pl/problemset/problem/YY6-3ua-C1rt7q-97laWc0UP/site/",
    "uniqueID": "https://szkopul.edu.pl/problemset/problem/YY6-3ua-C1rt7q-97laWc0UP/site/"
  },
  {
    "source": "DMOJ",
    "name": "Investment",
    "id": "tle17c1p6",
    "difficulty": "Hard",
    "starred": false,
    "tags": ["BCC"],
    "solID": "",
    "solQuality": "ok",
    "url": "https://dmoj.ca/problem/tle17c1p6",
    "uniqueID": "https://dmoj.ca/problem/tle17c1p6"
  },
  {
    "source": "CEOI",
    "name": "2015 - Pipes",
    "id": "CEOI15_pipes",
    "difficulty": "Hard",
    "starred": false,
    "tags": ["BCC"],
    "solID": "https://ceoi2015.fi.muni.cz/solutions/solutions1.pdf",
    "solQuality": "ok",
    "url": "https://oj.uz/problem/view/CEOI15_pipes",
    "uniqueID": "https://oj.uz/problem/view/CEOI15_pipes"
  },
  {
    "source": "Plat",
    "name": "Push a Box",
    "id": "769",
    "difficulty": "Very Hard",
    "starred": false,
    "tags": ["BCC"],
    "solID": "",
    "solQuality": "ok",
    "url": "http://www.usaco.org/index.php?page=viewproblem2&cpid=769",
    "uniqueID": "http://www.usaco.org/index.php?page=viewproblem2&cpid=769"
  }
]
